anymal_belief_state_encoder_decoder_pytorch/__init__.py
anymal_belief_state_encoder_decoder_pytorch/networks.py
anymal_belief_state_encoder_decoder_pytorch/ppo.py
anymal_belief_state_encoder_decoder_pytorch/running.py
anymal_belief_state_encoder_decoder_pytorch/trainer.py
anymal_belief_state_encoder_decoder_pytorch-0.0.21.dist-info/licenses/LICENSE
anymal_belief_state_encoder_decoder_pytorch-0.0.21.dist-info/METADATA
anymal_belief_state_encoder_decoder_pytorch-0.0.21.dist-info/WHEEL
anymal_belief_state_encoder_decoder_pytorch-0.0.21.dist-info/top_level.txt
anymal_belief_state_encoder_decoder_pytorch-0.0.21.dist-info/RECORD
