Metadata-Version: 2.4
Name: anymal-belief-state-encoder-decoder-pytorch
Version: 0.0.21
Summary: Anymal Belief-state Encoder Decoder - Pytorch
Home-page: https://github.com/lucidrains/anymal-belief-state-encoder-decoder-pytorch
Author: Phil Wang
Author-email: lucidrains@gmail.com
License: MIT
Keywords: artificial intelligence,deep learning,attention gating,belief state,robotics
Classifier: Development Status :: 4 - Beta
Classifier: Intended Audience :: Developers
Classifier: Topic :: Scientific/Engineering :: Artificial Intelligence
Classifier: License :: OSI Approved :: MIT License
Classifier: Programming Language :: Python :: 3.6
License-File: LICENSE
Requires-Dist: assoc-scan>=0.0.2
Requires-Dist: einops>=0.8
Requires-Dist: torch>=2.2
Dynamic: author
Dynamic: author-email
Dynamic: classifier
Dynamic: home-page
Dynamic: keywords
Dynamic: license
Dynamic: license-file
Dynamic: requires-dist
Dynamic: summary
